README
setup.py
bambu_oembed/__init__.py
bambu_oembed/managers.py
bambu_oembed/models.py
bambu_oembed/urls.py
bambu_oembed/views.py
bambu_oembed.egg-info/PKG-INFO
bambu_oembed.egg-info/SOURCES.txt
bambu_oembed.egg-info/dependency_links.txt
bambu_oembed.egg-info/requires.txt
bambu_oembed.egg-info/top_level.txt
bambu_oembed/migrations/0001_initial.py
bambu_oembed/migrations/__init__.py
bambu_oembed/static/oembed/bambu.oembed.js
bambu_oembed/templatetags/__init__.py
bambu_oembed/templatetags/oembed.py