Metadata-Version: 1.1
Name: bambu-oembed
Version: 2.5
Summary: Embed resources like YouTube videos, tweets and Flickr images by entering their URL on a single line of text. Methodology inspired by WordPress
Home-page: https://github.com/iamsteadman/bambu-oembed
Author: Steadman
Author-email: mark@steadman.io
License: UNKNOWN
Platform: UNKNOWN
Classifier: Development Status :: 4 - Beta
Classifier: Environment :: Web Environment
Classifier: Framework :: Django
